{"info":{"file":"src/core/ui/routines/UiChromeExtensionRoutine.js","fileShort":"core/ui/routines/UiChromeExtensionRoutine.js","fileSafe":"core_ui_routines_UiChromeExtensionRoutine_js","link":"files/core_ui_routines_UiChromeExtensionRoutine_js/index.html"},"complexity":{"aggregate":{"line":2,"complexity":{"sloc":{"physical":162,"logical":89},"cyclomatic":8,"halstead":{"operators":{"distinct":19,"total":330,"identifiers":["__stripped__"]},"operands":{"distinct":107,"total":346,"identifiers":["__stripped__"]},"length":676,"vocabulary":126,"difficulty":30.719626168224302,"volume":4716.641228285944,"effort":144893.45530257848,"bugs":1.5722137427619813,"time":8049.636405698805},"params":10}},"functions":[{"name":"<anonymous>","line":10,"complexity":{"sloc":{"physical":152,"logical":17},"cyclomatic":1,"halstead":{"operators":{"distinct":4,"total":62,"identifiers":["__stripped__"]},"operands":{"distinct":18,"total":62,"identifiers":["__stripped__"]},"length":124,"vocabulary":22,"difficulty":6.888888888888889,"volume":552.9695207110249,"effort":3809.3455871203937,"bugs":0.18432317357034161,"time":211.63031039557742},"params":0}},{"name":"UiChromeExtensionRoutine","line":11,"complexity":{"sloc":{"physical":4,"logical":2},"cyclomatic":1,"halstead":{"operators":{"distinct":2,"total":4,"identifiers":["__stripped__"]},"operands":{"distinct":4,"total":7,"identifiers":["__stripped__"]},"length":11,"vocabulary":6,"difficulty":1.75,"volume":28.43458750793272,"effort":49.76052813888226,"bugs":0.009478195835977574,"time":2.764473785493459},"params":1}},{"name":"<anonymous>.getDescription","line":15,"complexity":{"sloc":{"physical":3,"logical":1},"cyclomatic":1,"halstead":{"operators":{"distinct":3,"total":3,"identifiers":["__stripped__"]},"operands":{"distinct":3,"total":3,"identifiers":["__stripped__"]},"length":6,"vocabulary":6,"difficulty":1.5,"volume":15.509775004326936,"effort":23.264662506490403,"bugs":0.005169925001442312,"time":1.292481250360578},"params":0}},{"name":"<anonymous>.getIcon","line":19,"complexity":{"sloc":{"physical":3,"logical":1},"cyclomatic":1,"halstead":{"operators":{"distinct":3,"total":4,"identifiers":["__stripped__"]},"operands":{"distinct":4,"total":4,"identifiers":["__stripped__"]},"length":8,"vocabulary":7,"difficulty":1.5,"volume":22.458839376460833,"effort":33.68825906469125,"bugs":0.007486279792153611,"time":1.871569948038403},"params":0}},{"name":"<anonymous>.getId","line":23,"complexity":{"sloc":{"physical":3,"logical":1},"cyclomatic":1,"halstead":{"operators":{"distinct":3,"total":4,"identifiers":["__stripped__"]},"operands":{"distinct":4,"total":4,"identifiers":["__stripped__"]},"length":8,"vocabulary":7,"difficulty":1.5,"volume":22.458839376460833,"effort":33.68825906469125,"bugs":0.007486279792153611,"time":1.871569948038403},"params":0}},{"name":"<anonymous>.getName","line":27,"complexity":{"sloc":{"physical":3,"logical":1},"cyclomatic":1,"halstead":{"operators":{"distinct":3,"total":3,"identifiers":["__stripped__"]},"operands":{"distinct":3,"total":3,"identifiers":["__stripped__"]},"length":6,"vocabulary":6,"difficulty":1.5,"volume":15.509775004326936,"effort":23.264662506490403,"bugs":0.005169925001442312,"time":1.292481250360578},"params":0}},{"name":"<anonymous>.getNotice","line":31,"complexity":{"sloc":{"physical":3,"logical":1},"cyclomatic":1,"halstead":{"operators":{"distinct":3,"total":3,"identifiers":["__stripped__"]},"operands":{"distinct":3,"total":3,"identifiers":["__stripped__"]},"length":6,"vocabulary":6,"difficulty":1.5,"volume":15.509775004326936,"effort":23.264662506490403,"bugs":0.005169925001442312,"time":1.292481250360578},"params":0}},{"name":"<anonymous>.getInstallButtonLabel","line":35,"complexity":{"sloc":{"physical":3,"logical":1},"cyclomatic":1,"halstead":{"operators":{"distinct":3,"total":3,"identifiers":["__stripped__"]},"operands":{"distinct":3,"total":3,"identifiers":["__stripped__"]},"length":6,"vocabulary":6,"difficulty":1.5,"volume":15.509775004326936,"effort":23.264662506490403,"bugs":0.005169925001442312,"time":1.292481250360578},"params":0}},{"name":"<anonymous>.install","line":39,"complexity":{"sloc":{"physical":28,"logical":3},"cyclomatic":1,"halstead":{"operators":{"distinct":6,"total":9,"identifiers":["__stripped__"]},"operands":{"distinct":6,"total":9,"identifiers":["__stripped__"]},"length":18,"vocabulary":12,"difficulty":4.5,"volume":64.52932501298082,"effort":290.3819625584137,"bugs":0.02150977500432694,"time":16.132331253245205},"params":1}},{"name":"<anonymous>","line":41,"complexity":{"sloc":{"physical":2,"logical":0},"cyclomatic":1,"halstead":{"operators":{"distinct":0,"total":0,"identifiers":["__stripped__"]},"operands":{"distinct":0,"total":0,"identifiers":["__stripped__"]},"length":0,"time":0,"bugs":0,"effort":0,"volume":0,"difficulty":0,"vocabulary":0},"params":0}},{"name":"<anonymous>","line":44,"complexity":{"sloc":{"physical":22,"logical":10},"cyclomatic":3,"halstead":{"operators":{"distinct":11,"total":34,"identifiers":["__stripped__"]},"operands":{"distinct":24,"total":36,"identifiers":["__stripped__"]},"length":70,"vocabulary":35,"difficulty":8.25,"volume":359.0498111861476,"effort":2962.1609422857177,"bugs":0.11968327039538254,"time":164.564496793651},"params":1}},{"name":"<anonymous>","line":62,"complexity":{"sloc":{"physical":3,"logical":1},"cyclomatic":1,"halstead":{"operators":{"distinct":2,"total":2,"identifiers":["__stripped__"]},"operands":{"distinct":2,"total":3,"identifiers":["__stripped__"]},"length":5,"vocabulary":4,"difficulty":1.5,"volume":10,"effort":15,"bugs":0.0033333333333333335,"time":0.8333333333333334},"params":1}},{"name":"<anonymous>.isInstalled","line":68,"complexity":{"sloc":{"physical":28,"logical":15},"cyclomatic":3,"halstead":{"operators":{"distinct":14,"total":42,"identifiers":["__stripped__"]},"operands":{"distinct":23,"total":39,"identifiers":["__stripped__"]},"length":81,"vocabulary":37,"difficulty":11.869565217391305,"volume":421.96572261594497,"effort":5008.549664093608,"bugs":0.14065524087198167,"time":278.25275911631155},"params":1}},{"name":"doCallback","line":71,"complexity":{"sloc":{"physical":5,"logical":1},"cyclomatic":1,"halstead":{"operators":{"distinct":3,"total":3,"identifiers":["__stripped__"]},"operands":{"distinct":4,"total":4,"identifiers":["__stripped__"]},"length":7,"vocabulary":7,"difficulty":1.5,"volume":19.651484454403228,"effort":29.47722668160484,"bugs":0.00655049481813441,"time":1.6376237045336022},"params":1}},{"name":"<anonymous>","line":72,"complexity":{"sloc":{"physical":3,"logical":1},"cyclomatic":1,"halstead":{"operators":{"distinct":1,"total":1,"identifiers":["__stripped__"]},"operands":{"distinct":2,"total":2,"identifiers":["__stripped__"]},"length":3,"vocabulary":3,"difficulty":0.5,"volume":4.754887502163469,"effort":2.3774437510817346,"bugs":0.0015849625007211565,"time":0.1320802083934297},"params":0}},{"name":"<anonymous>.start","line":97,"complexity":{"sloc":{"physical":18,"logical":7},"cyclomatic":1,"halstead":{"operators":{"distinct":8,"total":35,"identifiers":["__stripped__"]},"operands":{"distinct":23,"total":36,"identifiers":["__stripped__"]},"length":71,"vocabulary":31,"difficulty":6.260869565217392,"volume":351.7479380374682,"effort":2202.2479598867576,"bugs":0.11724931267915607,"time":122.34710888259764},"params":1}},{"name":"<anonymous>","line":98,"complexity":{"sloc":{"physical":2,"logical":0},"cyclomatic":1,"halstead":{"operators":{"distinct":0,"total":0,"identifiers":["__stripped__"]},"operands":{"distinct":0,"total":0,"identifiers":["__stripped__"]},"length":0,"time":0,"bugs":0,"effort":0,"volume":0,"difficulty":0,"vocabulary":0},"params":0}},{"name":"<anonymous>","line":109,"complexity":{"sloc":{"physical":2,"logical":0},"cyclomatic":1,"halstead":{"operators":{"distinct":0,"total":0,"identifiers":["__stripped__"]},"operands":{"distinct":0,"total":0,"identifiers":["__stripped__"]},"length":0,"time":0,"bugs":0,"effort":0,"volume":0,"difficulty":0,"vocabulary":0},"params":0}},{"name":"<anonymous>.stop","line":116,"complexity":{"sloc":{"physical":6,"logical":2},"cyclomatic":1,"halstead":{"operators":{"distinct":8,"total":10,"identifiers":["__stripped__"]},"operands":{"distinct":9,"total":11,"identifiers":["__stripped__"]},"length":21,"vocabulary":17,"difficulty":4.888888888888889,"volume":85.83671966625714,"effort":419.64618503503493,"bugs":0.02861223988875238,"time":23.313676946390828},"params":1}},{"name":"<anonymous>","line":117,"complexity":{"sloc":{"physical":2,"logical":0},"cyclomatic":1,"halstead":{"operators":{"distinct":0,"total":0,"identifiers":["__stripped__"]},"operands":{"distinct":0,"total":0,"identifiers":["__stripped__"]},"length":0,"time":0,"bugs":0,"effort":0,"volume":0,"difficulty":0,"vocabulary":0},"params":0}},{"name":"<anonymous>.uninstall","line":123,"complexity":{"sloc":{"physical":6,"logical":2},"cyclomatic":1,"halstead":{"operators":{"distinct":6,"total":8,"identifiers":["__stripped__"]},"operands":{"distinct":7,"total":9,"identifiers":["__stripped__"]},"length":17,"vocabulary":13,"difficulty":3.8571428571428577,"volume":62.907475208398566,"effort":242.64311866096594,"bugs":0.02096915840279952,"time":13.480173258942552},"params":1}},{"name":"<anonymous>","line":124,"complexity":{"sloc":{"physical":2,"logical":0},"cyclomatic":1,"halstead":{"operators":{"distinct":0,"total":0,"identifiers":["__stripped__"]},"operands":{"distinct":0,"total":0,"identifiers":["__stripped__"]},"length":0,"time":0,"bugs":0,"effort":0,"volume":0,"difficulty":0,"vocabulary":0},"params":0}},{"name":"<anonymous>._geti18n","line":130,"complexity":{"sloc":{"physical":3,"logical":1},"cyclomatic":1,"halstead":{"operators":{"distinct":4,"total":7,"identifiers":["__stripped__"]},"operands":{"distinct":6,"total":7,"identifiers":["__stripped__"]},"length":14,"vocabulary":10,"difficulty":2.3333333333333335,"volume":46.50699332842308,"effort":108.51631776632053,"bugs":0.01550233110947436,"time":6.02868432035114},"params":1}},{"name":"<anonymous>._getInstallPath","line":134,"complexity":{"sloc":{"physical":5,"logical":2},"cyclomatic":2,"halstead":{"operators":{"distinct":8,"total":19,"identifiers":["__stripped__"]},"operands":{"distinct":16,"total":22,"identifiers":["__stripped__"]},"length":41,"vocabulary":24,"difficulty":5.5,"volume":187.98346252956745,"effort":1033.909043912621,"bugs":0.06266115417652249,"time":57.43939132847894},"params":0}},{"name":"<anonymous>._getDestinationCrxPath","line":140,"complexity":{"sloc":{"physical":5,"logical":2},"cyclomatic":2,"halstead":{"operators":{"distinct":7,"total":17,"identifiers":["__stripped__"]},"operands":{"distinct":15,"total":20,"identifiers":["__stripped__"]},"length":37,"vocabulary":22,"difficulty":4.666666666666666,"volume":164.99896988958,"effort":769.9951928180399,"bugs":0.05499965662986,"time":42.777510712113326},"params":0}},{"name":"<anonymous>._moveCrxAndGetPath","line":146,"complexity":{"sloc":{"physical":14,"logical":9},"cyclomatic":2,"halstead":{"operators":{"distinct":8,"total":34,"identifiers":["__stripped__"]},"operands":{"distinct":24,"total":38,"identifiers":["__stripped__"]},"length":72,"vocabulary":32,"difficulty":6.333333333333333,"volume":360,"effort":2280,"bugs":0.12,"time":126.66666666666667},"params":0}}],"maintainability":75.97422767735881,"params":0.38461538461538464,"module":"core/ui/routines/UiChromeExtensionRoutine.js"},"jshint":{"messages":[]}}